bfc/__init__.py
bfc/__main__.py
bfcc-1.0.0.dist-info/LICENSE
bfcc-1.0.0.dist-info/METADATA
bfcc-1.0.0.dist-info/WHEEL
bfcc-1.0.0.dist-info/entry_points.txt
bfcc-1.0.0.dist-info/top_level.txt
bfcc-1.0.0.dist-info/RECORD
